drf_to_s3
drf_to_s3/views
