Metadata-Version: 1.1
Name: drf-to-s3
Version: 0.7.6
Summary: Django REST Framework Interface for direct upload to S3
Home-page: https://github.com/bodylabs/drf-to-s3
Author: Body Labs
Author-email: paul.melnikow@bodylabs.com
License: MIT
Platform: UNKNOWN
Classifier: Development Status :: 3 - Alpha
Classifier: Environment :: Web Environment
Classifier: Framework :: Django
Classifier: Intended Audience :: Developers
Classifier: License :: OSI Approved :: MIT License
Classifier: Operating System :: OS Independent
Classifier: Programming Language :: Python
Classifier: Topic :: Internet :: WWW/HTTP
